{
  "album" : {
    "album_type" : "album",
    "artists" : [ {
      "external_urls" : {
        "spotify" : "https://open.spotify.com/artist/4gFssfOmWNY3LfIZ3zyoy4"
      },
      "href" : "https://api.spotify.com/v1/artists/4gFssfOmWNY3LfIZ3zyoy4",
      "id" : "4gFssfOmWNY3LfIZ3zyoy4",
      "name" : "Punch Brothers",
      "type" : "artist",
      "uri" : "spotify:artist:4gFssfOmWNY3LfIZ3zyoy4"
    } ],
    "available_markets" : [ "AD", "AE", "AR", "AT", "AU", "BE", "BG", "BH", "BO", "BR", "CA", "CH", "CL", "CO", "CR", "CY", "CZ", "DE", "DK", "DO", "DZ", "EC", "EE", "EG", "ES", "FI", "FR", "GB", "GR", "GT", "HK", "HN", "HU", "ID", "IE", "IL", "IS", "IT", "JO", "JP", "KW", "LB", "LI", "LT", "LU", "LV", "MA", "MC", "MT", "MX", "MY", "NI", "NL", "NO", "NZ", "OM", "PA", "PE", "PH", "PL", "PS", "PT", "PY", "QA", "RO", "SA", "SE", "SG", "SK", "SV", "TH", "TN", "TR", "TW", "US", "UY", "VN", "ZA" ],
    "external_urls" : {
      "spotify" : "https://open.spotify.com/album/2Jx5MfwDujgz2rFFDVocYl"
    },
    "href" : "https://api.spotify.com/v1/albums/2Jx5MfwDujgz2rFFDVocYl",
    "id" : "2Jx5MfwDujgz2rFFDVocYl",
    "images" : [ {
      "height" : 640,
      "url" : "https://i.scdn.co/image/4bf099621979190622150264a772f7a645b1b08f",
      "width" : 640
    }, {
      "height" : 300,
      "url" : "https://i.scdn.co/image/d9dd7c18ddeac54e940cf86f854ebefe1e0e90ee",
      "width" : 300
    }, {
      "height" : 64,
      "url" : "https://i.scdn.co/image/ff44efb5f7b000916263571f8fd22ac7c8a72eb6",
      "width" : 64
    } ],
    "name" : "All Ashore",
    "release_date" : "2018-07-20",
    "release_date_precision" : "day",
    "total_tracks" : 9,
    "type" : "album",
    "uri" : "spotify:album:2Jx5MfwDujgz2rFFDVocYl"
  },
  "artists" : [ {
    "external_urls" : {
      "spotify" : "https://open.spotify.com/artist/4gFssfOmWNY3LfIZ3zyoy4"
    },
    "href" : "https://api.spotify.com/v1/artists/4gFssfOmWNY3LfIZ3zyoy4",
    "id" : "4gFssfOmWNY3LfIZ3zyoy4",
    "name" : "Punch Brothers",
    "type" : "artist",
    "uri" : "spotify:artist:4gFssfOmWNY3LfIZ3zyoy4"
  } ],
  "available_markets" : [ "AD", "AE", "AR", "AT", "AU", "BE", "BG", "BH", "BO", "BR", "CA", "CH", "CL", "CO", "CR", "CY", "CZ", "DE", "DK", "DO", "DZ", "EC", "EE", "EG", "ES", "FI", "FR", "GB", "GR", "GT", "HK", "HN", "HU", "ID", "IE", "IL", "IS", "IT", "JO", "JP", "KW", "LB", "LI", "LT", "LU", "LV", "MA", "MC", "MT", "MX", "MY", "NI", "NL", "NO", "NZ", "OM", "PA", "PE", "PH", "PL", "PS", "PT", "PY", "QA", "RO", "SA", "SE", "SG", "SK", "SV", "TH", "TN", "TR", "TW", "US", "UY", "VN", "ZA" ],
  "disc_number" : 1,
  "duration_ms" : 267453,
  "explicit" : false,
  "external_ids" : {
    "isrc" : "USNO11800342"
  },
  "external_urls" : {
    "spotify" : "https://open.spotify.com/track/6kgZy9S3QvDSKkXhBwVXMT"
  },
  "href" : "https://api.spotify.com/v1/tracks/6kgZy9S3QvDSKkXhBwVXMT",
  "id" : "6kgZy9S3QvDSKkXhBwVXMT",
  "is_local" : false,
  "name" : "Three Dots and a Dash",
  "popularity" : 39,
  "preview_url" : "https://p.scdn.co/mp3-preview/77f97783da84f35d7dd9db5d641e88c8e55c1445?cid=55fa4e0de6184a4abd1a8cf0de5f5b1d",
  "track_number" : 3,
  "type" : "track",
  "uri" : "spotify:track:6kgZy9S3QvDSKkXhBwVXMT"
}